translate_pdf_word/HandleJs.py
translate_pdf_word/Word2word.py
translate_pdf_word/__init__.py
translate_pdf_word/translate.py
translate_pdf_word-0.0.2.dist-info/LICENSE
translate_pdf_word-0.0.2.dist-info/METADATA
translate_pdf_word-0.0.2.dist-info/WHEEL
translate_pdf_word-0.0.2.dist-info/top_level.txt
translate_pdf_word-0.0.2.dist-info/RECORD
