Metadata-Version: 2.1
Name: translate-pdf-word
Version: 0.0.2
Summary: A package for translating pdf or word files into Chinese versions
Home-page: https://github.com/xmlongan/translate-pdf-word
Author: Yanfeng Wu
Author-email: yanfeng1223@126.com
License: UNKNOWN
Platform: UNKNOWN
Classifier: Programming Language :: Python :: 3
Classifier: License :: OSI Approved :: MIT License
Classifier: Operating System :: OS Independent
